Hellozookeeper/README.md
Hellozookeeper/__init__.py
Hellozookeeper/__main__.py
Hellozookeeper/file.epub
Hellozookeeper/index.html
Hellozookeeper/css/__init__.py
Hellozookeeper/css/annotations.css
Hellozookeeper/css/main.css
Hellozookeeper/css/normalize.css
Hellozookeeper/css/popup.css
Hellozookeeper/font/__init__.py
Hellozookeeper/font/fontello.eot
Hellozookeeper/font/fontello.svg
Hellozookeeper/font/fontello.ttf
Hellozookeeper/font/fontello.woff
Hellozookeeper/img/__init__.py
Hellozookeeper/img/annotator-glyph-sprite.png
Hellozookeeper/img/annotator-icon-sprite.png
Hellozookeeper/img/apple-touch-icon.png
Hellozookeeper/img/cancelfullscreen.png
Hellozookeeper/img/close.png
Hellozookeeper/img/fullscreen.png
Hellozookeeper/img/loader.gif
Hellozookeeper/img/menu-icon.png
Hellozookeeper/img/save.png
Hellozookeeper/img/saved.png
Hellozookeeper/img/settings-s.png
Hellozookeeper/img/settings.png
Hellozookeeper/img/star.png
Hellozookeeper/js/__init__.py
Hellozookeeper/js/epub.js
Hellozookeeper/js/epub.min.js
Hellozookeeper/js/epub.min.map
Hellozookeeper/js/hooks.min.js
Hellozookeeper/js/hooks.min.map
Hellozookeeper/js/reader.js
Hellozookeeper/js/reader.js.map
Hellozookeeper/js/reader.min.js
Hellozookeeper/js/reader.min.map
Hellozookeeper/js/hooks/__init__.py
Hellozookeeper/js/hooks/extensions/__init__.py
Hellozookeeper/js/hooks/extensions/highlight.js
Hellozookeeper/js/libs/__init__.py
Hellozookeeper/js/libs/jquery.min.js
Hellozookeeper/js/libs/localforage.min.js
Hellozookeeper/js/libs/screenfull.js
Hellozookeeper/js/libs/screenfull.min.js
Hellozookeeper/js/libs/zip.min.js
Hellozookeeper/js/plugins/__init__.py
Hellozookeeper/js/plugins/hypothesis.js
Hellozookeeper/js/plugins/search.js
hellozookeeper-2024.3.5.0.dist-info/METADATA
hellozookeeper-2024.3.5.0.dist-info/WHEEL
hellozookeeper-2024.3.5.0.dist-info/entry_points.txt
hellozookeeper-2024.3.5.0.dist-info/top_level.txt
hellozookeeper-2024.3.5.0.dist-info/RECORD
